.gitignore
LICENSE-MIT
MANIFEST.in
README.md
setup.py
ttapi.py
examples/autobop.py
examples/blacklist.py
examples/chat_bot.py
examples/users_list.py
ttapi.egg-info/PKG-INFO
ttapi.egg-info/SOURCES.txt
ttapi.egg-info/dependency_links.txt
ttapi.egg-info/requires.txt
ttapi.egg-info/top_level.txt