Metadata-Version: 1.0
Name: ttapi
Version: 1.1.0
Summary: Allows you to create bots for turntable.fm.
Home-page: https://github.com/alaingilbert/Turntable-API/tree/python_ttapi
Author: Alain Gilbert
Author-email: alain.gilbert.15@gmail.com
License: MIT
Keywords: turntable bot
Platform: UNKNOWN
Classifier: Environment :: Console
Classifier: License :: OSI Approved :: MIT License
Classifier: Intended Audience :: Developers
Classifier: Natural Language :: English
Classifier: Operating System :: OS Independent
Classifier: Programming Language :: Python :: 2.6
Classifier: Programming Language :: Python :: 2.7
Classifier: Topic :: Utilities
